OppOpPopInit/__init__.py
OppOpPopInit/aliases.py
OppOpPopInit/initialiser.py
OppOpPopInit/main.py
OppOpPopInit/oppositor.py
OppOpPopInit/plotting.py
OppOpPopInit/utils.py
OppOpPopInit-2.0.1.dist-info/LICENSE
OppOpPopInit-2.0.1.dist-info/METADATA
OppOpPopInit-2.0.1.dist-info/WHEEL
OppOpPopInit-2.0.1.dist-info/top_level.txt
OppOpPopInit-2.0.1.dist-info/RECORD
