Metadata-Version: 2.1
Name: OppOpPopInit
Version: 2.0.1
Summary: PyPI package containing opposition learning operators and population initializers for evolutionary algorithms
Home-page: https://github.com/PasaOpasen/opp-op-pop-init
Author: Demetry Pascal
Author-email: qtckpuhdsa@gmail.com
Maintainer: Demetry Pascal
License: UNKNOWN
Keywords: opposition-based-learning,optimization,evolutionary algorithms,fast,easy,evolution,generator
Platform: UNKNOWN
Classifier: Programming Language :: Python :: 3.8
Classifier: License :: OSI Approved :: MIT License
Classifier: Operating System :: OS Independent
Classifier: Topic :: Software Development :: Libraries :: Python Modules
License-File: LICENSE
